mistaker/__init__.py
mistaker/address.py
mistaker/base.py
mistaker/cli.py
mistaker/constants.py
mistaker/date.py
mistaker/email.py
mistaker/generator.py
mistaker/license_number.py
mistaker/name.py
mistaker/number.py
mistaker/word.py
mistaker-0.4.2.dist-info/METADATA
mistaker-0.4.2.dist-info/WHEEL
mistaker-0.4.2.dist-info/entry_points.txt
mistaker-0.4.2.dist-info/licenses/LICENSE
mistaker-0.4.2.dist-info/RECORD
