Metadata-Version: 2.4
Name: mistaker
Version: 0.4.2
Summary: A package for emulating common data entry errors
Project-URL: Homepage, https://github.com/xdotcommer/mistaker_py
Project-URL: Bug Tracker, https://github.com/xdotcommer/mistaker_py/issues
Author-email: Michael Cowden <mike@novate.ai>
License-File: LICENSE
Classifier: License :: OSI Approved :: MIT License
Classifier: Operating System :: OS Independent
Classifier: Programming Language :: Python :: 3
Classifier: Programming Language :: Python :: 3.10
Classifier: Programming Language :: Python :: 3.11
Classifier: Programming Language :: Python :: 3.12
Requires-Python: >=3.10
Requires-Dist: nicknames>=0.1.11
Requires-Dist: usaddress>=0.5.11
Provides-Extra: test
Requires-Dist: pytest-cov>=4.0; extra == 'test'
Requires-Dist: pytest>=7.0; extra == 'test'
